compare_it/__init__.py
compare_it/diff.py
compare_it/forms/__init__.py
compare_it/forms/compare_configs.py
compare_it-0.0.6.dist-info/LICENSE
compare_it-0.0.6.dist-info/METADATA
compare_it-0.0.6.dist-info/WHEEL
compare_it-0.0.6.dist-info/top_level.txt
compare_it-0.0.6.dist-info/RECORD
